<?xml version="1.0" encoding="utf-8"?>
<resources>
    <string name="date_time">dd/MM, EEE</string>
    <string name="date_time_12">dd/MM, EEE</string>
    <string name="location">Mövcud</string>
    <string name="resident_city">Seçildi</string>
    <string name="talkback_TimeDesc">DQWZ vaxtı</string>
    <string name="talkback_date_time">d MMMM, EEEE</string>
    <string name="talkback_date_time_12">d MMMM, EEEE</string>
    <string name="talkback_location">Cari məkanınızda vaxt</string>
    <string name="talkback_resident_city">Seçilən məkanınızda vaxt</string>
    <string name="clock_local">Local</string>
    <string name="clock_city">City</string>
</resources>
